HISTORY.rst
LICENSE.txt
MANIFEST.in
README.md
requirements.txt
setup.py
MultiPlanarUNet/__init__.py
MultiPlanarUNet.egg-info/PKG-INFO
MultiPlanarUNet.egg-info/SOURCES.txt
MultiPlanarUNet.egg-info/dependency_links.txt
MultiPlanarUNet.egg-info/entry_points.txt
MultiPlanarUNet.egg-info/requires.txt
MultiPlanarUNet.egg-info/top_level.txt
MultiPlanarUNet/augmentation/__init__.py
MultiPlanarUNet/augmentation/augmenters.py
MultiPlanarUNet/augmentation/elastic_deformation.py
MultiPlanarUNet/bin/__init__.py
MultiPlanarUNet/bin/branch.py
MultiPlanarUNet/bin/cv_experiment.py
MultiPlanarUNet/bin/cv_split.py
MultiPlanarUNet/bin/init_project.py
MultiPlanarUNet/bin/mp.py
MultiPlanarUNet/bin/predict.py
MultiPlanarUNet/bin/predict_3D.py
MultiPlanarUNet/bin/run_tests.py
MultiPlanarUNet/bin/summary.py
MultiPlanarUNet/bin/toy_data.py
MultiPlanarUNet/bin/train.py
MultiPlanarUNet/bin/train_fusion.py
MultiPlanarUNet/bin/trim_channels.py
MultiPlanarUNet/bin/defaults/.DS_Store
MultiPlanarUNet/bin/defaults/__init__.py
MultiPlanarUNet/bin/defaults/3D/train_hparams.yaml
MultiPlanarUNet/bin/defaults/MultiPlanar/train_hparams.yaml
MultiPlanarUNet/bin/defaults/MultiTask/task_1.yaml
MultiPlanarUNet/bin/defaults/MultiTask/task_2.yaml
MultiPlanarUNet/bin/defaults/MultiTask/train_hparams.yaml
MultiPlanarUNet/bin/version/__init__.py
MultiPlanarUNet/bin/version/version_controller.py
MultiPlanarUNet/callbacks/__init__.py
MultiPlanarUNet/callbacks/callbacks.py
MultiPlanarUNet/callbacks/funcs.py
MultiPlanarUNet/callbacks/mcp_clean.py
MultiPlanarUNet/callbacks/utility_callbacks.py
MultiPlanarUNet/callbacks/validation.py
MultiPlanarUNet/database/__init__.py
MultiPlanarUNet/database/db_conn.py
MultiPlanarUNet/database/default_inserts.py
MultiPlanarUNet/database/default_tables.py
MultiPlanarUNet/errors/__init__.py
MultiPlanarUNet/errors/deprecated_warnings.py
MultiPlanarUNet/errors/image_errors.py
MultiPlanarUNet/errors/implementation_change_errors.py
MultiPlanarUNet/evaluate/__init__.py
MultiPlanarUNet/evaluate/loss_functions.py
MultiPlanarUNet/evaluate/metrics.py
MultiPlanarUNet/hyperparameters/__init__.py
MultiPlanarUNet/hyperparameters/hparams.py
MultiPlanarUNet/image/__init__.py
MultiPlanarUNet/image/auditor.py
