Metadata-Version: 2.1
Name: MultiPlanarUNet
Version: 0.2.3
Summary: Multi-Planar UNet for autonomous segmentation of 3D medical images
Home-page: https://github.com/perslev/MultiPlanarUNet
Author: Mathias Perslev
Author-email: map@di.ku.dk
License: LICENSE.txt
Platform: UNKNOWN
Classifier: Development Status :: 3 - Alpha
Classifier: Environment :: Console
Classifier: Operating System :: POSIX
Classifier: Programming Language :: Python :: 3
Classifier: Programming Language :: Python :: 3.5
Classifier: Programming Language :: Python :: 3.6
Classifier: Programming Language :: Python :: 3.7
Classifier: License :: OSI Approved :: MIT License
